snowmate_common-0.4.5.dist-info/METADATA
snowmate_common-0.4.5.dist-info/WHEEL
snowmate_common-0.4.5.dist-info/RECORD
snowmate_common-0.4.5.dist-info/top_level.txt
snowmate_common/name_extractor.cpython-39-x86_64-linux-gnu.so
snowmate_common/sender.py
snowmate_common/__init__.py
snowmate_common/consts/__init__.py
snowmate_common/consts/should_mock.py
snowmate_common/utils/object_wrapper.py
snowmate_common/utils/hash.py
snowmate_common/utils/object_wrapper.cpython-39-x86_64-linux-gnu.so
snowmate_common/utils/functions_data.py
snowmate_common/utils/compressing.py
snowmate_common/utils/special_unpicklers.py
snowmate_common/utils/__init__.py
snowmate_common/utils/projects.py
snowmate_common/utils/protobuff/protobuf_builder.py
snowmate_common/utils/protobuff/__init__.py
snowmate_common/utils/pydantic/custom_types.py
snowmate_common/utils/pydantic/base_model_default_config.py
snowmate_common/utils/pydantic/__init__.py
snowmate_common/messages_data/__init__.py
snowmate_common/messages_data/messages.py
snowmate_common/auth/__init__.py
snowmate_common/auth/authorizer.py
