Metadata-Version: 2.1
Name: snowmate-common
Version: 0.4.5
Summary: snowmate_common
License: UNKNOWN
Platform: UNKNOWN
Requires-Dist: pydantic
Requires-Dist: requests
Requires-Dist: python-dateutil
Requires-Dist: betterproto
Requires-Dist: bson
Requires-Dist: PyJWT
Requires-Dist: astor
